{
  "summary": {
    "board_id": "refboard_v1",
    "marker_count": 44,
    "charuco_corner_count": 70,
    "confidence": 1.0,
    "board_outline_image": [
      [
        430.53021240234375,
        431.4754638671875
      ],
      [
        1177.2547607421875,
        440.031005859375
      ],
      [
        1154.8555908203125,
        969.8409423828125
      ],
      [
        413.75823974609375,
        946.9845581054688
      ]
    ],
    "board_reprojection_rmse_px": 0.2007969319820404
  },
  "markers": [
    {
      "id": 26,
      "corners_image": [
        [
          1036.0,
          712.0
        ],
        [
          1086.0,
          713.0
        ],
        [
          1084.0,
          761.0
        ],
        [
          1034.0,
          759.0
        ]
      ]
    },
    {
      "id": 9,
      "corners_image": [
        [
          976.0,
          513.0
        ],
        [
          1026.0,
          514.0
        ],
        [
          1023.0,
          562.0
        ],
        [
          974.0,
          561.0
        ]
      ]
    },
    {
      "id": 20,
      "corners_image": [
        [
          971.0,
          644.0
        ],
        [
          1020.0,
          645.0
        ],
        [
          1018.0,
          693.0
        ],
        [
          969.0,
          692.0
        ]
      ]
    },
    {
      "id": 36,
      "corners_image": [
        [
          895.0,
          839.0
        ],
        [
          944.0,
          841.0
        ],
        [
          942.0,
          888.0
        ],
        [
          892.0,
          886.0
        ]
      ]
    },
    {
      "id": 17,
      "corners_image": [
        [
          565.0,
          637.0
        ],
        [
          614.0,
          639.0
        ],
        [
          612.0,
          685.0
        ],
        [
          564.0,
          684.0
        ]
      ]
    },
    {
      "id": 28,
      "corners_image": [
        [
          561.0,
          766.0
        ],
        [
          609.0,
          767.0
        ],
        [
          607.0,
          814.0
        ],
        [
          559.0,
          813.0
        ]
      ]
    },
    {
      "id": 22,
      "corners_image": [
        [
          497.0,
          700.0
        ],
        [
          545.0,
          702.0
        ],
        [
          543.0,
          748.0
        ],
        [
          495.0,
          747.0
        ]
      ]
    },
    {
      "id": 21,
      "corners_image": [
        [
          1108.0,
          647.0
        ],
        [
          1159.0,
          649.0
        ],
        [
          1157.0,
          696.0
        ],
        [
          1106.0,
          695.0
        ]
      ]
    },
    {
      "id": 10,
      "corners_image": [
        [
          1114.0,
          515.0
        ],
        [
          1164.0,
          515.0
        ],
        [
          1162.0,
          564.0
        ],
        [
          1112.0,
          563.0
        ]
      ]
    },
    {
      "id": 32,
      "corners_image": [
        [
          1103.0,
          779.0
        ],
        [
          1153.0,
          780.0
        ],
        [
          1151.0,
          828.0
        ],
        [
          1101.0,
          827.0
        ]
      ]
    },
    {
      "id": 15,
      "corners_image": [
        [
          1042.0,
          580.0
        ],
        [
          1092.0,
          581.0
        ],
        [
          1090.0,
          629.0
        ],
        [
          1040.0,
          628.0
        ]
      ]
    },
    {
      "id": 37,
      "corners_image": [
        [
          1031.0,
          843.0
        ],
        [
          1081.0,
          844.0
        ],
        [
          1079.0,
          892.0
        ],
        [
          1029.0,
          891.0
        ]
      ]
    },
    {
      "id": 43,
      "corners_image": [
        [
          1097.0,
          911.0
        ],
        [
          1148.0,
          913.0
        ],
        [
          1145.0,
          960.0
        ],
        [
          1095.0,
          958.0
        ]
      ]
    },
    {
      "id": 4,
      "corners_image": [
        [
          1048.0,
          447.0
        ],
        [
          1097.0,
          448.0
        ],
        [
          1095.0,
          496.0
        ],
        [
          1045.0,
          495.0
        ]
      ]
    },
    {
      "id": 3,
      "corners_image": [
        [
          910.0,
          446.0
        ],
        [
          959.0,
          446.0
        ],
        [
          958.0,
          494.0
        ],
        [
          908.0,
          494.0
        ]
      ]
    },
    {
      "id": 42,
      "corners_image": [
        [
          960.0,
          907.0
        ],
        [
          1010.0,
          908.0
        ],
        [
          1007.0,
          956.0
        ],
        [
          958.0,
          954.0
        ]
      ]
    },
    {
      "id": 31,
      "corners_image": [
        [
          965.0,
          776.0
        ],
        [
          1015.0,
          777.0
        ],
        [
          1012.0,
          825.0
        ],
        [
          963.0,
          823.0
        ]
      ]
    },
    {
      "id": 8,
      "corners_image": [
        [
          839.0,
          511.0
        ],
        [
          889.0,
          512.0
        ],
        [
          887.0,
          559.0
        ],
        [
          837.0,
          558.0
        ]
      ]
    },
    {
      "id": 13,
      "corners_image": [
        [
          769.0,
          575.0
        ],
        [
          818.0,
          576.0
        ],
        [
          816.0,
          624.0
        ],
        [
          767.0,
          623.0
        ]
      ]
    },
    {
      "id": 14,
      "corners_image": [
        [
          904.0,
          578.0
        ],
        [
          954.0,
          578.0
        ],
        [
          952.0,
          626.0
        ],
        [
          903.0,
          625.0
        ]
      ]
    },
    {
      "id": 30,
      "corners_image": [
        [
          830.0,
          772.0
        ],
        [
          878.0,
          774.0
        ],
        [
          877.0,
          821.0
        ],
        [
          827.0,
          820.0
        ]
      ]
    },
    {
      "id": 2,
      "corners_image": [
        [
          774.0,
          444.0
        ],
        [
          823.0,
          445.0
        ],
        [
          820.0,
          493.0
        ],
        [
          772.0,
          492.0
        ]
      ]
    },
    {
      "id": 25,
      "corners_image": [
        [
          899.0,
          709.0
        ],
        [
          949.0,
          710.0
        ],
        [
          947.0,
          757.0
        ],
        [
          898.0,
          756.0
        ]
      ]
    },
    {
      "id": 19,
      "corners_image": [
        [
          834.0,
          642.0
        ],
        [
          883.0,
          643.0
        ],
        [
          882.0,
          690.0
        ],
        [
          832.0,
          689.0
        ]
      ]
    },
    {
      "id": 24,
      "corners_image": [
        [
          764.0,
          706.0
        ],
        [
          813.0,
          707.0
        ],
        [
          811.0,
          754.0
        ],
        [
          762.0,
          753.0
        ]
      ]
    },
    {
      "id": 12,
      "corners_image": [
        [
          634.0,
          573.0
        ],
        [
          683.0,
          574.0
        ],
        [
          681.0,
          621.0
        ],
        [
          632.0,
          620.0
        ]
      ]
    },
    {
      "id": 41,
      "corners_image": [
        [
          824.0,
          903.0
        ],
        [
          873.0,
          904.0
        ],
        [
          872.0,
          951.0
        ],
        [
          822.0,
          949.0
        ]
      ]
    },
    {
      "id": 29,
      "corners_image": [
        [
          694.0,
          769.0
        ],
        [
          743.0,
          771.0
        ],
        [
          740.0,
          818.0
        ],
        [
          692.0,
          816.0
        ]
      ]
    },
    {
      "id": 18,
      "corners_image": [
        [
          699.0,
          639.0
        ],
        [
          748.0,
          641.0
        ],
        [
          745.0,
          688.0
        ],
        [
          697.0,
          686.0
        ]
      ]
    },
    {
      "id": 35,
      "corners_image": [
        [
          759.0,
          836.0
        ],
        [
          808.0,
          837.0
        ],
        [
          806.0,
          884.0
        ],
        [
          757.0,
          882.0
        ]
      ]
    },
    {
      "id": 1,
      "corners_image": [
        [
          639.0,
          443.0
        ],
        [
          687.0,
          443.0
        ],
        [
          685.0,
          491.0
        ],
        [
          637.0,
          490.0
        ]
      ]
    },
    {
      "id": 7,
      "corners_image": [
        [
          704.0,
          509.0
        ],
        [
          752.0,
          510.0
        ],
        [
          751.0,
          557.0
        ],
        [
          702.0,
          556.0
        ]
      ]
    },
    {
      "id": 40,
      "corners_image": [
        [
          689.0,
          899.0
        ],
        [
          738.0,
          900.0
        ],
        [
          736.0,
          947.0
        ],
        [
          688.0,
          946.0
        ]
      ]
    },
    {
      "id": 23,
      "corners_image": [
        [
          629.0,
          703.0
        ],
        [
          678.0,
          704.0
        ],
        [
          676.0,
          751.0
        ],
        [
          628.0,
          750.0
        ]
      ]
    },
    {
      "id": 34,
      "corners_image": [
        [
          625.0,
          832.0
        ],
        [
          673.0,
          834.0
        ],
        [
          671.0,
          881.0
        ],
        [
          623.0,
          879.0
        ]
      ]
    },
    {
      "id": 6,
      "corners_image": [
        [
          570.0,
          507.0
        ],
        [
          618.0,
          508.0
        ],
        [
          616.0,
          555.0
        ],
        [
          568.0,
          554.0
        ]
      ]
    },
    {
      "id": 16,
      "corners_image": [
        [
          433.0,
          634.0
        ],
        [
          481.0,
          635.0
        ],
        [
          479.0,
          682.0
        ],
        [
          431.0,
          681.0
        ]
      ]
    },
    {
      "id": 39,
      "corners_image": [
        [
          556.0,
          895.0
        ],
        [
          604.0,
          896.0
        ],
        [
          603.0,
          943.0
        ],
        [
          555.0,
          942.0
        ]
      ]
    },
    {
      "id": 0,
      "corners_image": [
        [
          505.0,
          441.0
        ],
        [
          553.0,
          442.0
        ],
        [
          552.0,
          489.0
        ],
        [
          504.0,
          488.0
        ]
      ]
    },
    {
      "id": 11,
      "corners_image": [
        [
          501.0,
          571.0
        ],
        [
          549.0,
          572.0
        ],
        [
          547.0,
          619.0
        ],
        [
          499.0,
          617.0
        ]
      ]
    },
    {
      "id": 5,
      "corners_image": [
        [
          437.0,
          505.0
        ],
        [
          485.0,
          506.0
        ],
        [
          483.0,
          553.0
        ],
        [
          436.0,
          552.0
        ]
      ]
    },
    {
      "id": 27,
      "corners_image": [
        [
          429.0,
          763.0
        ],
        [
          476.0,
          764.0
        ],
        [
          475.0,
          811.0
        ],
        [
          427.0,
          809.0
        ]
      ]
    },
    {
      "id": 33,
      "corners_image": [
        [
          492.0,
          829.0
        ],
        [
          540.0,
          830.0
        ],
        [
          538.0,
          877.0
        ],
        [
          491.0,
          875.0
        ]
      ]
    },
    {
      "id": 38,
      "corners_image": [
        [
          425.0,
          891.0
        ],
        [
          472.0,
          893.0
        ],
        [
          471.0,
          939.0
        ],
        [
          423.0,
          938.0
        ]
      ]
    }
  ],
  "charuco_corners": [
    {
      "id": 0,
      "image_xy": [
        494.56048583984375,
        497.5351257324219
      ],
      "board_xy_mm": [
        15.0,
        15.0
      ]
    },
    {
      "id": 1,
      "image_xy": [
        560.8523559570312,
        498.1982116699219
      ],
      "board_xy_mm": [
        30.0,
        15.0
      ]
    },
    {
      "id": 2,
      "image_xy": [
        627.8038940429688,
        499.2478332519531
      ],
      "board_xy_mm": [
        45.0,
        15.0
      ]
    },
    {
      "id": 3,
      "image_xy": [
        694.6878662109375,
        500.0280456542969
      ],
      "board_xy_mm": [
        60.0,
        15.0
      ]
    },
    {
      "id": 4,
      "image_xy": [
        762.6340942382812,
        501.0809326171875
      ],
      "board_xy_mm": [
        75.0,
        15.0
      ]
    },
    {
      "id": 5,
      "image_xy": [
        830.1785278320312,
        501.8249816894531
      ],
      "board_xy_mm": [
        90.0,
        15.0
      ]
    },
    {
      "id": 6,
      "image_xy": [
        898.3941040039062,
        502.9869689941406
      ],
      "board_xy_mm": [
        105.0,
        15.0
      ]
    },
    {
      "id": 7,
      "image_xy": [
        966.8118286132812,
        503.6962890625
      ],
      "board_xy_mm": [
        120.0,
        15.0
      ]
    },
    {
      "id": 8,
      "image_xy": [
        1035.8109130859375,
        504.8088073730469
      ],
      "board_xy_mm": [
        135.0,
        15.0
      ]
    },
    {
      "id": 9,
      "image_xy": [
        1104.7537841796875,
        505.52813720703125
      ],
      "board_xy_mm": [
        150.0,
        15.0
      ]
    },
    {
      "id": 10,
      "image_xy": [
        492.2955322265625,
        561.9306030273438
      ],
      "board_xy_mm": [
        15.0,
        30.0
      ]
    },
    {
      "id": 11,
      "image_xy": [
        558.9361572265625,
        563.1551513671875
      ],
      "board_xy_mm": [
        30.0,
        30.0
      ]
    },
    {
      "id": 12,
      "image_xy": [
        625.1853637695312,
        564.072998046875
      ],
      "board_xy_mm": [
        45.0,
        30.0
      ]
    },
    {
      "id": 13,
      "image_xy": [
        692.64306640625,
        565.345458984375
      ],
      "board_xy_mm": [
        60.0,
        30.0
      ]
    },
    {
      "id": 14,
      "image_xy": [
        760.150634765625,
        566.4526977539062
      ],
      "board_xy_mm": [
        75.0,
        30.0
      ]
    },
    {
      "id": 15,
      "image_xy": [
        827.9664916992188,
        567.7039794921875
      ],
      "board_xy_mm": [
        90.0,
        30.0
      ]
    },
    {
      "id": 16,
      "image_xy": [
        895.8870239257812,
        568.7330932617188
      ],
      "board_xy_mm": [
        105.0,
        30.0
      ]
    },
    {
      "id": 17,
      "image_xy": [
        964.3695678710938,
        569.962890625
      ],
      "board_xy_mm": [
        120.0,
        30.0
      ]
    },
    {
      "id": 18,
      "image_xy": [
        1033.0401611328125,
        570.9322509765625
      ],
      "board_xy_mm": [
        135.0,
        30.0
      ]
    },
    {
      "id": 19,
      "image_xy": [
        1102.1876220703125,
        572.0505981445312
      ],
      "board_xy_mm": [
        150.0,
        30.0
      ]
    },
    {
      "id": 20,
      "image_xy": [
        490.4737243652344,
        626.8025512695312
      ],
      "board_xy_mm": [
        15.0,
        45.0
      ]
    },
    {
      "id": 21,
      "image_xy": [
        556.62060546875,
        628.0008544921875
      ],
      "board_xy_mm": [
        30.0,
        45.0
      ]
    },
    {
      "id": 22,
      "image_xy": [
        623.1845703125,
        629.357421875
      ],
      "board_xy_mm": [
        45.0,
        45.0
      ]
    },
    {
      "id": 23,
      "image_xy": [
        689.95654296875,
        630.2919311523438
      ],
      "board_xy_mm": [
        60.0,
        45.0
      ]
    },
    {
      "id": 24,
      "image_xy": [
        757.7532958984375,
        631.852294921875
      ],
      "board_xy_mm": [
        75.0,
        45.0
      ]
    },
    {
      "id": 25,
      "image_xy": [
        825.27490234375,
        633.0037231445312
      ],
      "board_xy_mm": [
        90.0,
        45.0
      ]
    },
    {
      "id": 26,
      "image_xy": [
        893.3458862304688,
        634.38427734375
      ],
      "board_xy_mm": [
        105.0,
        45.0
      ]
    },
    {
      "id": 27,
      "image_xy": [
        961.643310546875,
        635.3807373046875
      ],
      "board_xy_mm": [
        120.0,
        45.0
      ]
    },
    {
      "id": 28,
      "image_xy": [
        1030.2833251953125,
        636.9967041015625
      ],
      "board_xy_mm": [
        135.0,
        45.0
      ]
    },
    {
      "id": 29,
      "image_xy": [
        1099.3485107421875,
        638.0940551757812
      ],
      "board_xy_mm": [
        150.0,
        45.0
      ]
    },
    {
      "id": 30,
      "image_xy": [
        488.1023864746094,
        691.2387084960938
      ],
      "board_xy_mm": [
        15.0,
        60.0
      ]
    },
    {
      "id": 31,
      "image_xy": [
        554.37890625,
        692.932373046875
      ],
      "board_xy_mm": [
        30.0,
        60.0
      ]
    },
    {
      "id": 32,
      "image_xy": [
        620.9224243164062,
        694.0390625
      ],
      "board_xy_mm": [
        45.0,
        60.0
      ]
    },
    {
      "id": 33,
      "image_xy": [
        687.75732421875,
        695.7702026367188
      ],
      "board_xy_mm": [
        60.0,
        60.0
      ]
    },
    {
      "id": 34,
      "image_xy": [
        755.3251342773438,
        696.8773803710938
      ],
      "board_xy_mm": [
        75.0,
        60.0
      ]
    },
    {
      "id": 35,
      "image_xy": [
        822.9303588867188,
        698.593994140625
      ],
      "board_xy_mm": [
        90.0,
        60.0
      ]
    },
    {
      "id": 36,
      "image_xy": [
        890.7350463867188,
        699.7734985351562
      ],
      "board_xy_mm": [
        105.0,
        60.0
      ]
    },
    {
      "id": 37,
      "image_xy": [
        959.0433959960938,
        701.3631591796875
      ],
      "board_xy_mm": [
        120.0,
        60.0
      ]
    },
    {
      "id": 38,
      "image_xy": [
        1027.6412353515625,
        702.7797241210938
      ],
      "board_xy_mm": [
        135.0,
        60.0
      ]
    },
    {
      "id": 39,
      "image_xy": [
        1096.626708984375,
        704.3091430664062
      ],
      "board_xy_mm": [
        150.0,
        60.0
      ]
    },
    {
      "id": 40,
      "image_xy": [
        485.9788818359375,
        756.2326049804688
      ],
      "board_xy_mm": [
        15.0,
        75.0
      ]
    },
    {
      "id": 41,
      "image_xy": [
        552.0995483398438,
        757.6799926757812
      ],
      "board_xy_mm": [
        30.0,
        75.0
      ]
    },
    {
      "id": 42,
      "image_xy": [
        618.3840942382812,
        759.4638671875
      ],
      "board_xy_mm": [
        45.0,
        75.0
      ]
    },
    {
      "id": 43,
      "image_xy": [
        685.5258178710938,
        760.776611328125
      ],
      "board_xy_mm": [
        60.0,
        75.0
      ]
    },
    {
      "id": 44,
      "image_xy": [
        752.7813110351562,
        762.6714477539062
      ],
      "board_xy_mm": [
        75.0,
        75.0
      ]
    },
    {
      "id": 45,
      "image_xy": [
        820.4450073242188,
        763.9656982421875
      ],
      "board_xy_mm": [
        90.0,
        75.0
      ]
    },
    {
      "id": 46,
      "image_xy": [
        888.1507568359375,
        765.8488159179688
      ],
      "board_xy_mm": [
        105.0,
        75.0
      ]
    },
    {
      "id": 47,
      "image_xy": [
        956.6166381835938,
        767.267578125
      ],
      "board_xy_mm": [
        120.0,
        75.0
      ]
    },
    {
      "id": 48,
      "image_xy": [
        1024.995361328125,
        768.9163208007812
      ],
      "board_xy_mm": [
        135.0,
        75.0
      ]
    },
    {
      "id": 49,
      "image_xy": [
        1093.9266357421875,
        770.6065673828125
      ],
      "board_xy_mm": [
        150.0,
        75.0
      ]
    },
    {
      "id": 50,
      "image_xy": [
        483.8910217285156,
        820.2978515625
      ],
      "board_xy_mm": [
        15.0,
        90.0
      ]
    },
    {
      "id": 51,
      "image_xy": [
        549.8523559570312,
        822.1907348632812
      ],
      "board_xy_mm": [
        30.0,
        90.0
      ]
    },
    {
      "id": 52,
      "image_xy": [
        616.2406005859375,
        823.925537109375
      ],
      "board_xy_mm": [
        45.0,
        90.0
      ]
    },
    {
      "id": 53,
      "image_xy": [
        682.8583374023438,
        825.9037475585938
      ],
      "board_xy_mm": [
        60.0,
        90.0
      ]
    },
    {
      "id": 54,
      "image_xy": [
        750.5931396484375,
        827.3095703125
      ],
      "board_xy_mm": [
        75.0,
        90.0
      ]
    },
    {
      "id": 55,
      "image_xy": [
        817.934326171875,
        829.168701171875
      ],
      "board_xy_mm": [
        90.0,
        90.0
      ]
    },
    {
      "id": 56,
      "image_xy": [
        885.76806640625,
        831.0101928710938
      ],
      "board_xy_mm": [
        105.0,
        90.0
      ]
    },
    {
      "id": 57,
      "image_xy": [
        953.7601318359375,
        832.9188842773438
      ],
      "board_xy_mm": [
        120.0,
        90.0
      ]
    },
    {
      "id": 58,
      "image_xy": [
        1022.22216796875,
        834.3464965820312
      ],
      "board_xy_mm": [
        135.0,
        90.0
      ]
    },
    {
      "id": 59,
      "image_xy": [
        1091.1253662109375,
        836.2657470703125
      ],
      "board_xy_mm": [
        150.0,
        90.0
      ]
    },
    {
      "id": 60,
      "image_xy": [
        481.5972595214844,
        884.76171875
      ],
      "board_xy_mm": [
        15.0,
        105.0
      ]
    },
    {
      "id": 61,
      "image_xy": [
        547.8981323242188,
        886.5764770507812
      ],
      "board_xy_mm": [
        30.0,
        105.0
      ]
    },
    {
      "id": 62,
      "image_xy": [
        614.0367431640625,
        888.598876953125
      ],
      "board_xy_mm": [
        45.0,
        105.0
      ]
    },
    {
      "id": 63,
      "image_xy": [
        680.7896728515625,
        890.3643188476562
      ],
      "board_xy_mm": [
        60.0,
        105.0
      ]
    },
    {
      "id": 64,
      "image_xy": [
        748.1561279296875,
        892.3147583007812
      ],
      "board_xy_mm": [
        75.0,
        105.0
      ]
    },
    {
      "id": 65,
      "image_xy": [
        815.6040649414062,
        894.2335815429688
      ],
      "board_xy_mm": [
        90.0,
        105.0
      ]
    },
    {
      "id": 66,
      "image_xy": [
        883.0732421875,
        896.3045654296875
      ],
      "board_xy_mm": [
        105.0,
        105.0
      ]
    },
    {
      "id": 67,
      "image_xy": [
        951.2975463867188,
        898.0869140625
      ],
      "board_xy_mm": [
        120.0,
        105.0
      ]
    },
    {
      "id": 68,
      "image_xy": [
        1019.5709228515625,
        900.1290283203125
      ],
      "board_xy_mm": [
        135.0,
        105.0
      ]
    },
    {
      "id": 69,
      "image_xy": [
        1088.53515625,
        901.9646606445312
      ],
      "board_xy_mm": [
        150.0,
        105.0
      ]
    }
  ]
}
